hmap/__init__.py
hmap/layout/__init__.py
hmap/layout/layout.py
hmap/plot/__init__.py
hmap/plot/basic.py
hmap-0.9.2.dist-info/LICENSE
hmap-0.9.2.dist-info/METADATA
hmap-0.9.2.dist-info/WHEEL
hmap-0.9.2.dist-info/top_level.txt
hmap-0.9.2.dist-info/RECORD
